django_heartbeat-2.2.4.dist-info/licenses/LICENSE
heartbeat/__init__.py
heartbeat/auth.py
heartbeat/settings.py
heartbeat/urls.py
heartbeat/views.py
heartbeat/checkers/__init__.py
heartbeat/checkers/build.py
heartbeat/checkers/databases.py
heartbeat/checkers/debug_mode.py
heartbeat/checkers/distribution_list.py
heartbeat/checkers/host.py
heartbeat/checkers/memcached_status.py
heartbeat/checkers/python.py
heartbeat/checkers/redis_status.py
django_heartbeat-2.2.4.dist-info/METADATA
django_heartbeat-2.2.4.dist-info/WHEEL
django_heartbeat-2.2.4.dist-info/top_level.txt
django_heartbeat-2.2.4.dist-info/RECORD
