Metadata-Version: 2.4
Name: django-heartbeat
Version: 2.2.4
Summary: A simple reusable app that checks and lists various information about your project and its dependencies
Author-email: PBS Core Services <pbsi-team-core-services@pbs.org>
License: The MIT License (MIT)
Project-URL: Homepage, https://github.com/pbs/django-heartbeat
Keywords: django,heartbeat,health check,dependency status
Classifier: Programming Language :: Python :: 3
Requires-Python: >=3.10
License-File: LICENSE
Requires-Dist: Django<5.3,>=4
Requires-Dist: psutil
Requires-Dist: setuptools
Dynamic: license-file
